omen2/__init__.py
omen2/codegen.py
omen2/errors.py
omen2/m2mhelper.py
omen2/object.py
omen2/omen.py
omen2/relation.py
omen2/selectable.py
omen2/table.py
omen2/types.py
omen2-2.1.5.dist-info/LICENSE
omen2-2.1.5.dist-info/METADATA
omen2-2.1.5.dist-info/WHEEL
omen2-2.1.5.dist-info/entry_points.txt
omen2-2.1.5.dist-info/top_level.txt
omen2-2.1.5.dist-info/RECORD
