Metadata-Version: 2.1
Name: omen2
Version: 2.1.5
Summary: Database object & cache manager
License: UNKNOWN
Platform: UNKNOWN
License-File: LICENSE
Requires-Dist: notanorm (>=3)
Requires-Dist: sqlglot (>=9)
